{"pos_tags": {"You": "PRON", "'ll": "AUX", "never": "ADV", "make": "VERB", "me": "PRON", "stay": "VERB", "\n": "SPACE", "So": "CCONJ", "take": "VERB", "your": "PRON", "weight": "NOUN", "off": "ADP", "of": "ADP", "I": "PRON", "know": "VERB", "every": "DET", "move": "NOUN", "wo": "AUX", "n't": "PART", "you": "PRON", "just": "ADV", "let": "VERB", "be": "AUX", "?": "PUNCT", "'ve": "AUX", "been": "AUX", "here": "ADV", "times": "NOUN", "before": "ADP", "But": "CCONJ", "was": "AUX", "too": "ADV", "blind": "ADJ", "to": "ADP", "see": "VERB", "That": "PRON", "seduce": "VERB", "man": "NOUN", "This": "DET", "time": "NOUN", ",": "PUNCT", "\n\n": "SPACE", "[": "X", "Pre": "NOUN", "-": "NOUN", "Chorus": "NOUN", "]": "PUNCT", "She": "PRON", "'s": "AUX", "saying": "VERB", "\"": "PUNCT", "okay": "ADJ", "Hey": "INTJ", "baby": "NOUN", "do": "AUX", "what": "PRON", "please": "VERB", "have": "VERB", "the": "DET", "stuff": "NOUN", "that": "PRON", "want": "VERB", "am": "AUX", "thing": "NOUN", "need": "VERB", "looked": "VERB", "deep": "ADV", "in": "ADP", "eyes": "NOUN", "touching": "VERB", "so": "ADV", "start": "VERB", "says": "VERB", "There": "PRON", "no": "INTJ", "turning": "NOUN", "back": "ADV", "trapped": "VERB", "her": "PRON", "heart": "NOUN", "Dirty": "ADJ", "Diana": "PROPN", "!": "PUNCT", "(": "PUNCT", "Oh": "INTJ", "oh": "INTJ", ")": "PUNCT", "likes": "VERB", "boys": "NOUN", "band": "NOUN", "knows": "VERB", "when": "SCONJ", "they": "PRON", "come": "VERB", "town": "NOUN", "Every": "DET", "musician": "NOUN", "fan": "NOUN", "After": "SCONJ", "curtain": "NOUN", "comes": "VERB", "down": "ADP", "waits": "VERB", "at": "ADP", "backstage": "NOUN", "doors": "NOUN", "For": "ADP", "those": "PRON", "who": "PRON", "prestige": "NOUN", "Who": "PRON", "promise": "VERB", "fortune": "NOUN", "and": "CCONJ", "fame": "NOUN", "A": "PRON", "life": "NOUN", "carefree": "ADJ", "night": "NOUN", "loving": "VERB", "freak": "NOUN", "can": "AUX", "taunt": "VERB", "And": "CCONJ", "care": "VERB", "say": "VERB", "go": "VERB", "far": "ADV", "everything": "PRON", "If": "SCONJ", "a": "DET", "star": "NOUN", "Interlude": "X", "It": "PRON", "-iana": "PROPN", "C'm": "PUNCT", "on": "ADP", "said": "VERB", "home": "NOUN", "'Cause": "SCONJ", "'m": "AUX", "real": "ADV", "tired": "ADJ", "hate": "VERB", "sleeping": "VERB", "alone": "ADV", "Why": "SCONJ", "with": "ADP", "My": "PRON", "probably": "ADV", "worried": "ADJ", "tonight": "NOUN", "did": "AUX", "call": "VERB", "phone": "NOUN", "To": "PART", "alright": "ADJ", "walked": "VERB", "up": "ADP", "all": "PRON", "yours": "PRON", "At": "ADP", "ran": "VERB", "Saying": "PROPN", "Baby": "PROPN", "unlock": "VERB", "door": "NOUN", "forgot": "VERB", "key": "ADJ", "He": "PRON", "not": "PART", "coming": "VERB", "Because": "SCONJ", "he": "PRON", "hey": "INTJ", "you-": "VERB", "Aaow": "PROPN", "no)77Embed": "SYM"}, "pos_tags_freq": {"PRON": 23, "AUX": 12, "ADV": 11, "VERB": 38, "SPACE": 2, "CCONJ": 4, "NOUN": 33, "ADP": 12, "DET": 5, "PART": 3, "PUNCT": 8, "ADJ": 8, "X": 2, "INTJ": 5, "PROPN": 5, "SCONJ": 6, "SYM": 1}, "word_frequency": {"Diana": 40, "Dirty": 36, "no": 31, "I": 21, "on": 17, "C'm": 16, "She": 13, "you": 12, "me": 12, "the": 11, "to": 7, "Hey": 7, "baby": 7, "wo": 6, "be": 5, "that": 5, "said": 5, "your": 4, "do": 4, "you-": 4, "in": 3, "That": 3, "what": 3, "want": 3, "have": 3, "Pre": 3, "Chorus": 3, "But": 3, "So": 2, "every": 2, "seduce": 2, "let": 2, "oh": 2, "so": 2, "saying": 2, "okay": 2, "thing": 2, "too": 2, "make": 2, "-iana": 2, "go": 2, "see": 2, "come": 2, "at": 2, "home": 2, "say": 2, "tonight": 2, "phone": 2, "alright": 2, "back": 2, "sleeping": 2, "with": 2, "You": 1, "'ll": 1, "never": 1, "stay": 1, "\n": 1, "take": 1, "weight": 1, "off": 1, "of": 1, "know": 1, "move": 1, "n't": 1, "just": 1, "?": 1, "'ve": 1, "been": 1, "here": 1, "times": 1, "before": 1, "was": 1, "blind": 1, "man": 1, "This": 1, "time": 1, ",": 1, "\n\n": 1, "[": 1, "-": 1, "]": 1, "'s": 1, "\"": 1, "please": 1, "stuff": 1, "am": 1, "need": 1, "looked": 1, "deep": 1, "eyes": 1, "touching": 1, "start": 1, "says": 1, "There": 1, "turning": 1, "trapped": 1, "her": 1, "heart": 1, "!": 1, "(": 1, "Oh": 1, ")": 1, "likes": 1, "boys": 1, "band": 1, "knows": 1, "when": 1, "they": 1, "town": 1, "Every": 1, "musician": 1, "fan": 1, "After": 1, "curtain": 1, "comes": 1, "down": 1, "waits": 1, "backstage": 1, "doors": 1, "For": 1, "those": 1, "who": 1, "prestige": 1, "Who": 1, "promise": 1, "fortune": 1, "and": 1, "fame": 1, "A": 1, "life": 1, "carefree": 1, "night": 1, "loving": 1, "freak": 1, "can": 1, "taunt": 1, "And": 1, "care": 1, "far": 1, "everything": 1, "If": 1, "a": 1, "star": 1, "Interlude": 1, "It": 1, "'Cause": 1, "'m": 1, "real": 1, "tired": 1, "hate": 1, "alone": 1, "Why": 1, "My": 1, "probably": 1, "worried": 1, "did": 1, "call": 1, "To": 1, "walked": 1, "up": 1, "all": 1, "yours": 1, "At": 1, "ran": 1, "Saying": 1, "Baby": 1, "unlock": 1, "door": 1, "forgot": 1, "key": 1, "He": 1, "not": 1, "coming": 1, "Because": 1, "he": 1, "hey": 1, "Aaow": 1, "no)77Embed": 1}, "named_entities": {"Diana": "PERSON", "Diana\nDirty Diana": "PERSON", "Diana\nDiana\nDirty Diana": "PERSON", "-iana\nC'm": "PERSON", "tonight": "TIME", "Diana\n\n": "PERSON"}, "dependency_parse": {"You": {"dep": "nsubj", "head": "make"}, "'ll": {"dep": "aux", "head": "be"}, "never": {"dep": "neg", "head": "make"}, "make": {"dep": "advcl", "head": "care"}, "me": {"dep": "pobj", "head": "with"}, "stay": {"dep": "ccomp", "head": "make"}, "\n": {"dep": "dep", "head": ")"}, "So": {"dep": "advmod", "head": "let"}, "take": {"dep": "conj", "head": "make"}, "your": {"dep": "poss", "head": "everything"}, "weight": {"dep": "dobj", "head": "take"}, "off": {"dep": "prep", "head": "take"}, "of": {"dep": "prep", "head": "off"}, "I": {"dep": "nsubj", "head": "forgot"}, "know": {"dep": "ROOT", "head": "know"}, "every": {"dep": "det", "head": "man"}, "move": {"dep": "dobj", "head": "know"}, "wo": {"dep": "aux", "head": "you-"}, "n't": {"dep": "neg", "head": "you-"}, "you": {"dep": "nsubj", "head": "come"}, "just": {"dep": "advmod", "head": "let"}, "let": {"dep": "xcomp", "head": "says"}, "be": {"dep": "ccomp", "head": "care"}, "?": {"dep": "punct", "head": "come"}, "'ve": {"dep": "aux", "head": "been"}, "been": {"dep": "ROOT", "head": "been"}, "here": {"dep": "advmod", "head": "been"}, "times": {"dep": "npadvmod", "head": "been"}, "before": {"dep": "prep", "head": "times"}, "But": {"dep": "cc", "head": "said"}, "was": {"dep": "ccomp", "head": "seduce"}, "too": {"dep": "advmod", "head": "far"}, "blind": {"dep": "acomp", "head": "was"}, "to": {"dep": "prep", "head": "ran"}, "see": {"dep": "ccomp", "head": "said"}, "That": {"dep": "nsubj", "head": "'s"}, "seduce": {"dep": "ROOT", "head": "seduce"}, "man": {"dep": "dobj", "head": "seduce"}, "This": {"dep": "det", "head": "time"}, "time": {"dep": "npadvmod", "head": "seduce"}, ",": {"dep": "punct", "head": "Diana"}, "\n\n": {"dep": "dep", "head": "Diana"}, "[": {"dep": "punct", "head": "walked"}, "Pre": {"dep": "nsubj", "head": "walked"}, "-": {"dep": "nsubj", "head": "walked"}, "Chorus": {"dep": "nsubj", "head": "walked"}, "]": {"dep": "punct", "head": "walked"}, "She": {"dep": "nsubj", "head": "said"}, "'s": {"dep": "aux", "head": "sleeping"}, "saying": {"dep": "ROOT", "head": "saying"}, "\"": {"dep": "punct", "head": "Diana"}, "okay": {"dep": "acomp", "head": "'s"}, "Hey": {"dep": "nmod", "head": "baby"}, "baby": {"dep": "nsubj", "head": "you-"}, "do": {"dep": "aux", "head": "come"}, "what": {"dep": "dobj", "head": "say"}, "please": {"dep": "ccomp", "head": "do"}, "have": {"dep": "ccomp", "head": "see"}, "the": {"dep": "det", "head": "key"}, "stuff": {"dep": "dobj", "head": "have"}, "that": {"dep": "pobj", "head": "At"}, "want": {"dep": "ccomp", "head": "say"}, "am": {"dep": "relcl", "head": "stuff"}, "thing": {"dep": "attr", "head": "be"}, "need": {"dep": "relcl", "head": "thing"}, "looked": {"dep": "conj", "head": "do"}, "deep": {"dep": "advmod", "head": "in"}, "in": {"dep": "prep", "head": "boys"}, "eyes": {"dep": "pobj", "head": "in"}, "touching": {"dep": "ROOT", "head": "touching"}, "so": {"dep": "advmod", "head": "carefree"}, "start": {"dep": "advcl", "head": "touching"}, "says": {"dep": "ccomp", "head": "touching"}, "There": {"dep": "expl", "head": "'s"}, "no": {"dep": "intj", "head": "Diana"}, "turning": {"dep": "attr", "head": "'s"}, "back": {"dep": "advmod", "head": "coming"}, "trapped": {"dep": "ccomp", "head": "says"}, "her": {"dep": "poss", "head": "heart"}, "heart": {"dep": "pobj", "head": "in"}, "Dirty": {"dep": "amod", "head": "Diana"}, "Diana": {"dep": "ROOT", "head": "Diana"}, "!": {"dep": "punct", "head": "on"}, "(": {"dep": "punct", "head": "Diana"}, "Oh": {"dep": "intj", "head": "no"}, "oh": {"dep": "intj", "head": "Oh"}, ")": {"dep": "punct", "head": "no"}, "likes": {"dep": "ROOT", "head": "likes"}, "boys": {"dep": "dobj", "head": "likes"}, "band": {"dep": "pobj", "head": "in"}, "knows": {"dep": "ROOT", "head": "knows"}, "when": {"dep": "advmod", "head": "come"}, "they": {"dep": "nsubj", "head": "come"}, "come": {"dep": "ccomp", "head": "said"}, "town": {"dep": "compound", "head": "fan"}, "Every": {"dep": "det", "head": "musician"}, "musician": {"dep": "poss", "head": "fan"}, "fan": {"dep": "pobj", "head": "to"}, "After": {"dep": "mark", "head": "comes"}, "curtain": {"dep": "nsubj", "head": "comes"}, "comes": {"dep": "advcl", "head": "come"}, "down": {"dep": "prep", "head": "comes"}, "waits": {"dep": "ccomp", "head": "knows"}, "at": {"dep": "prep", "head": "'s"}, "backstage": {"dep": "compound", "head": "doors"}, "doors": {"dep": "pobj", "head": "at"}, "For": {"dep": "prep", "head": "knows"}, "those": {"dep": "pobj", "head": "For"}, "who": {"dep": "nsubj", "head": "have"}, "prestige": {"dep": "dobj", "head": "have"}, "Who": {"dep": "nsubj", "head": "promise"}, "promise": {"dep": "relcl", "head": "prestige"}, "fortune": {"dep": "poss", "head": "life"}, "and": {"dep": "cc", "head": "fortune"}, "fame": {"dep": "compound", "head": "A"}, "A": {"dep": "conj", "head": "fortune"}, "life": {"dep": "dobj", "head": "promise"}, "carefree": {"dep": "acomp", "head": "'s"}, "night": {"dep": "npadvmod", "head": "loving"}, "loving": {"dep": "amod", "head": "thing"}, "freak": {"dep": "attr", "head": "be"}, "can": {"dep": "aux", "head": "taunt"}, "taunt": {"dep": "relcl", "head": "freak"}, "And": {"dep": "cc", "head": "care"}, "care": {"dep": "ROOT", "head": "care"}, "say": {"dep": "xcomp", "head": "call"}, "go": {"dep": "xcomp", "head": "have"}, "far": {"dep": "advmod", "head": "be"}, "everything": {"dep": "attr", "head": "be"}, "If": {"dep": "mark", "head": "make"}, "a": {"dep": "det", "head": "Diana"}, "star": {"dep": "nmod", "head": "Diana"}, "Interlude": {"dep": "dep", "head": "Dirty"}, "It": {"dep": "nsubj", "head": "'s"}, "-iana": {"dep": "appos", "head": "-iana"}, "C'm": {"dep": "punct", "head": "on"}, "on": {"dep": "ROOT", "head": "on"}, "said": {"dep": "ccomp", "head": "forgot"}, "home": {"dep": "pobj", "head": "at"}, "'Cause": {"dep": "mark", "head": "forgot"}, "'m": {"dep": "ccomp", "head": "said"}, "real": {"dep": "advmod", "head": "tired"}, "tired": {"dep": "acomp", "head": "'m"}, "hate": {"dep": "ROOT", "head": "hate"}, "sleeping": {"dep": "advcl", "head": "coming"}, "alone": {"dep": "advmod", "head": "sleeping"}, "Why": {"dep": "advmod", "head": "come"}, "with": {"dep": "prep", "head": "sleeping"}, "My": {"dep": "poss", "head": "baby"}, "probably": {"dep": "advmod", "head": "worried"}, "worried": {"dep": "acomp", "head": "'s"}, "tonight": {"dep": "npadvmod", "head": "'m"}, "did": {"dep": "aux", "head": "call"}, "call": {"dep": "ccomp", "head": "'s"}, "phone": {"dep": "compound", "head": "Saying"}, "To": {"dep": "aux", "head": "say"}, "alright": {"dep": "acomp", "head": "'m"}, "walked": {"dep": "ccomp", "head": "say"}, "up": {"dep": "prt", "head": "walked"}, "all": {"dep": "dep", "head": "'m"}, "yours": {"dep": "attr", "head": "'m"}, "At": {"dep": "prep", "head": "ran"}, "ran": {"dep": "ccomp", "head": "'m"}, "Saying": {"dep": "pobj", "head": "to"}, "Baby": {"dep": "appos", "head": "Saying"}, "unlock": {"dep": "conj", "head": "said"}, "door": {"dep": "dobj", "head": "unlock"}, "forgot": {"dep": "ccomp", "head": "said"}, "key": {"dep": "dobj", "head": "forgot"}, "He": {"dep": "nsubj", "head": "coming"}, "not": {"dep": "neg", "head": "coming"}, "coming": {"dep": "ccomp", "head": "said"}, "Because": {"dep": "mark", "head": "sleeping"}, "he": {"dep": "nsubj", "head": "sleeping"}, "hey": {"dep": "intj", "head": "Hey"}, "you-": {"dep": "ROOT", "head": "you-"}, "Aaow": {"dep": "ROOT", "head": "Aaow"}, "no)77Embed": {"dep": "appos", "head": "Diana"}}, "text_classification": "Neutral", "text_similarity": {"Another Part of Me": 0.8080522551037298, "Bad": 0.8793326829661924, "I Just Can't Stop Loving You (with Siedah Garrett)": 0.7873207766033032, "Just Good Friends (feat. Stevie Wonder)": 0.8727935792510576, "Leave Me Alone": 0.8019925621001995, "Liberian Girl": 0.8528194189809118, "Man in the Mirror": 0.8625457746905328, "Smooth Criminal": 0.8783299560944142, "Speed Demon": 0.8697061848131664, "The Way You Make Me Feel": 0.8147976714926848}, "text_similarity_average": 0.8427690862096192, "word_vectors": {}, "text_lemmatization": {"Diana": 40, "I": 33, "dirty": 33, "no": 31, "on": 17, "you": 13, "she": 13, "the": 11, "say": 10, "be": 8, "to": 8, "that": 8, "hey": 8, "baby": 7, "will": 6, "do": 5, "so": 4, "your": 4, "come": 4, "every": 3, "but": 3, "Pre": 3, "chorus": 3, "what": 3, "have": 3, "want": 3, "in": 3, "Dirty": 3, "oh": 3, "at": 3, "make": 2, "know": 2, "let": 2, "time": 2, "too": 2, "see": 2, "seduce": 2, "okay": 2, "thing": 2, "back": 2, "door": 2, "who": 2, "and": 2, "a": 2, "go": 2, "home": 2, "sleep": 2, "with": 2, "tonight": 2, "phone": 2, "alright": 2, "he": 2, "never": 1, "stay": 1, "take": 1, "weight": 1, "off": 1, "of": 1, "move": 1, "just": 1, "here": 1, "before": 1, "blind": 1, "man": 1, "this": 1, "please": 1, "stuff": 1, "need": 1, "look": 1, "deep": 1, "eye": 1, "touch": 1, "start": 1, "there": 1, "turning": 1, "trap": 1, "her": 1, "heart": 1, "like": 1, "boy": 1, "band": 1, "when": 1, "they": 1, "town": 1, "musician": 1, "fan": 1, "after": 1, "curtain": 1, "down": 1, "wait": 1, "backstage": 1, "for": 1, "those": 1, "prestige": 1, "promise": 1, "fortune": 1, "fame": 1, "life": 1, "carefree": 1, "night": 1, "love": 1, "freak": 1, "can": 1, "taunt": 1, "care": 1, "far": 1, "everything": 1, "if": 1, "star": 1, "interlude": 1, "it": 1, "real": 1, "tired": 1, "hate": 1, "alone": 1, "why": 1, "my": 1, "probably": 1, "worried": 1, "call": 1, "walk": 1, "up": 1, "all": 1, "yours": 1, "run": 1, "Saying": 1, "Baby": 1, "unlock": 1, "forget": 1, "key": 1, "not": 1, "because": 1, "Aaow": 1}, "text_summarization": "[ a n d   i   d o n ' t   c a r e   w h a t   y o u   s a y \n i   w a n t   t o   g o   t o o   f a r \n i ' l l   b e   y o u r   e v e r y t h i n g \n i f   y o u   m a k e   m e   a   s t a r \" \n \n d i r t y   d i a n a ,   n o \n d i r t y   d i a n a ,   n o \n d i r t y   d i a n a ,   n o \n d i r t y   d i a n a \n d i r t y   d i a n a ,   n o \n d i r t y   d i a n a ,   n o \n d i r t y   d i a n a ,   n o \n d i r t y   d i a n a \n [ i n t e r l u d e ] \n d i a n a \n d i a n a \n d i r t y   d i a n a \n ,   ( d i r t y   d i a n a ) \n c ' m o n ! ,   ( d i r t y   d i a n a ) ]", "non_real_words_freq": [38, ["You'll", "I've", "[Pre-Chorus]", "\"That's", "\"There's", "that's", "[Pre-Chorus]", "\"That's", "night-loving", "don't", "-iana,", "-iana", "C'mon!", "I'm", "don't", "baby's", "didn't", "I'm", "[Pre-Chorus]", "\"I'm", "I'm", "C'mon!", "C'mon!", "C'mon!", "C'mon!", "C'mon!", "C'mon!", "C'mon!", "C'mon!", "C'mon!", "Aaow!", "C'mon!", "C'mon!", "C'mon!", "C'mon!", "C'mon!", "C'mon!", "no)77Embed"]]}