{"pos_tags": {"Why": "SCONJ", "?": "PUNCT", "\n\n": "SPACE", "Looking": "VERB", "out": "ADP", "across": "ADP", "the": "DET", "nighttime": "NOUN", "\n": "SPACE", "The": "DET", "city": "NOUN", "winks": "VERB", "a": "DET", "sleepless": "NOUN", "eye": "NOUN", "Hear": "VERB", "her": "PRON", "voice": "NOUN", ",": "PUNCT", "shake": "VERB", "my": "PRON", "window": "NOUN", "Sweet": "PROPN", "seducing": "NOUN", "sighs": "NOUN", "Get": "VERB", "me": "PRON", "into": "ADP", "Four": "NUM", "walls": "NOUN", "wo": "AUX", "n't": "PART", "hold": "VERB", "tonight": "NOUN", "If": "SCONJ", "this": "DET", "town": "NOUN", "is": "AUX", "just": "ADV", "an": "DET", "apple": "NOUN", "Then": "ADV", "let": "VERB", "take": "VERB", "bite": "NOUN", "they": "PRON", "say": "VERB", "why": "SCONJ", "(": "PUNCT", ")": "PUNCT", "Tell": "VERB", "them": "PRON", "that": "DET", "it": "PRON", "'s": "AUX", "human": "ADJ", "nature": "NOUN", "does": "AUX", "he": "PRON", "do": "VERB", "way": "NOUN", "Reaching": "VERB", "to": "PART", "touch": "VERB", "stranger": "NOUN", "Electric": "ADJ", "eyes": "NOUN", "are": "AUX", "everywhere": "ADV", "See": "VERB", "girl": "NOUN", "she": "PRON", "knows": "VERB", "I": "PRON", "'m": "AUX", "watching": "VERB", "She": "PRON", "likes": "VERB", "stare": "VERB", "Just": "ADV", "tell": "VERB", "giving": "VERB", "in": "ADP", "by": "ADP", "keeping": "VERB", "him": "PRON", "-": "PUNCT", "round": "ADJ", "like": "VERB", "livin": "NOUN", "'": "PUNCT", "lovin'": "NOUN", "That": "DET", "Oh": "INTJ", "morning": "NOUN", "heart": "NOUN", "begins": "VERB", "beat": "VERB", "shoulder": "NOUN", "dreaming": "VERB", "of": "ADP", "street": "NOUN", "Ooh": "INTJ", "ooh": "INTJ", "'em": "PRON", "!": "PUNCT", "Cha": "PROPN", "da": "ADJ", "cha": "ADV", "sha": "X", "Aah": "NOUN", "ah": "INTJ", "Da": "PROPN", "living": "VERB", "way)64Embed": "PROPN"}, "pos_tags_freq": {"SCONJ": 3, "PUNCT": 7, "SPACE": 2, "VERB": 26, "ADP": 6, "DET": 7, "NOUN": 25, "PRON": 12, "PROPN": 4, "NUM": 1, "AUX": 6, "PART": 2, "ADV": 5, "ADJ": 4, "INTJ": 4, "X": 1}, "word_frequency": {"Why": 61, "why": 37, "way": 18, "that": 16, "me": 13, "If": 11, "they": 10, "say": 10, "does": 10, "he": 10, "do": 10, "da": 8, "a": 7, "I": 7, "out": 5, "the": 5, "them": 5, "it": 5, "human": 5, "nature": 5, "sha": 5, "She": 5, "Oh": 5, "That": 5, "Tell": 4, "tell": 4, "giving": 4, "in": 4, "by": 4, "keeping": 4, "him": 4, "round": 4, "this": 4, "Ooh": 3, "like": 3, "nighttime": 2, "Looking": 2, "across": 2, "The": 2, "city": 2, "to": 2, "Reaching": 2, "touch": 2, "her": 2, "ooh": 2, "Aah": 2, "ah": 2, "?": 1, "\n\n": 1, "\n": 1, "winks": 1, "sleepless": 1, "eye": 1, "Hear": 1, "voice": 1, ",": 1, "shake": 1, "my": 1, "window": 1, "Sweet": 1, "seducing": 1, "sighs": 1, "Get": 1, "into": 1, "Four": 1, "walls": 1, "wo": 1, "n't": 1, "hold": 1, "tonight": 1, "town": 1, "is": 1, "just": 1, "an": 1, "apple": 1, "Then": 1, "let": 1, "take": 1, "bite": 1, "(": 1, ")": 1, "'s": 1, "stranger": 1, "Electric": 1, "eyes": 1, "are": 1, "everywhere": 1, "See": 1, "girl": 1, "she": 1, "knows": 1, "'m": 1, "watching": 1, "likes": 1, "stare": 1, "Just": 1, "-": 1, "livin": 1, "'": 1, "lovin'": 1, "morning": 1, "heart": 1, "begins": 1, "beat": 1, "shoulder": 1, "dreaming": 1, "of": 1, "street": 1, "'em": 1, "!": 1, "Cha": 1, "cha": 1, "Da": 1, "living": 1, "way)64Embed": 1}, "named_entities": {"nighttime": "TIME", "Sweet": "PERSON", "Four": "CARDINAL", "tonight": "TIME", "morning": "TIME", "Da-da-da-da-da-da-da-da": "PERSON"}, "dependency_parse": {"Why": {"dep": "ROOT", "head": "Why"}, "?": {"dep": "punct", "head": "why"}, "\n\n": {"dep": "dep", "head": "street"}, "Looking": {"dep": "advcl", "head": "begins"}, "out": {"dep": "prt", "head": "Reaching"}, "across": {"dep": "prep", "head": "Looking"}, "the": {"dep": "det", "head": "street"}, "nighttime": {"dep": "compound", "head": "Four"}, "\n": {"dep": "dep", "head": ")"}, "The": {"dep": "det", "head": "city"}, "city": {"dep": "poss", "head": "heart"}, "winks": {"dep": "ROOT", "head": "winks"}, "a": {"dep": "det", "head": "round"}, "sleepless": {"dep": "compound", "head": "eye"}, "eye": {"dep": "dobj", "head": "winks"}, "Hear": {"dep": "conj", "head": "winks"}, "her": {"dep": "poss", "head": "shoulder"}, "voice": {"dep": "dobj", "head": "Hear"}, ",": {"dep": "punct", "head": "why"}, "shake": {"dep": "conj", "head": "Hear"}, "my": {"dep": "poss", "head": "window"}, "window": {"dep": "dobj", "head": "shake"}, "Sweet": {"dep": "compound", "head": "seducing"}, "seducing": {"dep": "compound", "head": "sighs"}, "sighs": {"dep": "nsubj", "head": "Get"}, "Get": {"dep": "ccomp", "head": "shake"}, "me": {"dep": "dobj", "head": "do"}, "into": {"dep": "prep", "head": "Get"}, "Four": {"dep": "nummod", "head": "walls"}, "walls": {"dep": "pobj", "head": "into"}, "wo": {"dep": "aux", "head": "hold"}, "n't": {"dep": "neg", "head": "hold"}, "hold": {"dep": "conj", "head": "winks"}, "tonight": {"dep": "npadvmod", "head": "hold"}, "If": {"dep": "mark", "head": "say"}, "this": {"dep": "det", "head": "way"}, "town": {"dep": "nsubj", "head": "is"}, "is": {"dep": "advcl", "head": "hold"}, "just": {"dep": "advmod", "head": "apple"}, "an": {"dep": "det", "head": "apple"}, "apple": {"dep": "attr", "head": "is"}, "Then": {"dep": "advmod", "head": "let"}, "let": {"dep": "ROOT", "head": "let"}, "take": {"dep": "ccomp", "head": "let"}, "bite": {"dep": "dobj", "head": "take"}, "they": {"dep": "nsubj", "head": "say"}, "say": {"dep": "advcl", "head": "Why"}, "why": {"dep": "ROOT", "head": "why"}, "(": {"dep": "punct", "head": "way)64Embed"}, ")": {"dep": "punct", "head": "way"}, "Tell": {"dep": "conj", "head": "touch"}, "them": {"dep": "dobj", "head": "Tell"}, "that": {"dep": "det", "head": "way"}, "it": {"dep": "nsubj", "head": "'s"}, "'s": {"dep": "aux", "head": "giving"}, "human": {"dep": "amod", "head": "nature"}, "nature": {"dep": "attr", "head": "'s"}, "does": {"dep": "aux", "head": "do"}, "he": {"dep": "nsubj", "head": "do"}, "do": {"dep": "ROOT", "head": "do"}, "way": {"dep": "ROOT", "head": "way"}, "Reaching": {"dep": "xcomp", "head": "beat"}, "to": {"dep": "aux", "head": "beat"}, "touch": {"dep": "ROOT", "head": "touch"}, "stranger": {"dep": "amod", "head": "Electric"}, "Electric": {"dep": "amod", "head": "eyes"}, "eyes": {"dep": "dobj", "head": "touch"}, "are": {"dep": "ccomp", "head": "knows"}, "everywhere": {"dep": "advmod", "head": "are"}, "See": {"dep": "advcl", "head": "are"}, "girl": {"dep": "dobj", "head": "See"}, "she": {"dep": "nsubj", "head": "knows"}, "knows": {"dep": "ROOT", "head": "knows"}, "I": {"dep": "nsubj", "head": "like"}, "'m": {"dep": "aux", "head": "dreaming"}, "watching": {"dep": "ccomp", "head": "knows"}, "She": {"dep": "nsubj", "head": "giving"}, "likes": {"dep": "ROOT", "head": "likes"}, "stare": {"dep": "relcl", "head": "way"}, "Just": {"dep": "advmod", "head": "tell"}, "tell": {"dep": "ROOT", "head": "tell"}, "giving": {"dep": "ccomp", "head": "do"}, "in": {"dep": "prt", "head": "giving"}, "by": {"dep": "prep", "head": "giving"}, "keeping": {"dep": "pcomp", "head": "by"}, "him": {"dep": "dobj", "head": "keeping"}, "-": {"dep": "punct", "head": "da"}, "round": {"dep": "oprd", "head": "keeping"}, "like": {"dep": "ROOT", "head": "like"}, "livin": {"dep": "dobj", "head": "like"}, "'": {"dep": "punct", "head": "livin"}, "lovin'": {"dep": "advcl", "head": "like"}, "That": {"dep": "det", "head": "way)64Embed"}, "Oh": {"dep": "intj", "head": "why"}, "morning": {"dep": "pobj", "head": "across"}, "heart": {"dep": "nsubj", "head": "begins"}, "begins": {"dep": "ccomp", "head": "touch"}, "beat": {"dep": "xcomp", "head": "begins"}, "shoulder": {"dep": "dobj", "head": "touch"}, "dreaming": {"dep": "relcl", "head": "shoulder"}, "of": {"dep": "prep", "head": "dreaming"}, "street": {"dep": "pobj", "head": "of"}, "Ooh": {"dep": "intj", "head": "tell"}, "ooh": {"dep": "intj", "head": "tell"}, "'em": {"dep": "dobj", "head": "tell"}, "!": {"dep": "punct", "head": "tell"}, "Cha": {"dep": "npadvmod", "head": "Aah"}, "da": {"dep": "advmod", "head": "da"}, "cha": {"dep": "advmod", "head": "sha"}, "sha": {"dep": "punct", "head": "Cha"}, "Aah": {"dep": "ROOT", "head": "Aah"}, "ah": {"dep": "intj", "head": "Aah"}, "Da": {"dep": "compound", "head": "da"}, "living": {"dep": "xcomp", "head": "like"}, "way)64Embed": {"dep": "ROOT", "head": "way)64Embed"}}, "text_classification": "Neutral", "text_similarity": {"Baby Be Mine": 0.6999519423003123, "Beat It": 0.7460159233460699, "Billie Jean": 0.7379019584338594, "P.Y.T. (Pretty Young Thing)": 0.7532658692639815, "The Girl Is Mine (with Paul McCartney)": 0.5424677372744346, "The Lady in My Life": 0.698839815253347, "Thriller": 0.6905285161882697, "Wanna Be Startin' Somethin'": 0.7110480381861232}, "text_similarity_average": 0.6975024750307998, "word_vectors": {}, "text_lemmatization": {"why": 98, "that": 21, "I": 20, "do": 20, "way": 18, "they": 15, "he": 14, "if": 11, "say": 10, "tell": 8, "da": 8, "the": 7, "a": 7, "she": 6, "out": 5, "it": 5, "human": 5, "nature": 5, "oh": 5, "sha": 5, "this": 4, "like": 4, "give": 4, "in": 4, "by": 4, "keep": 4, "round": 4, "ooh": 3, "look": 2, "across": 2, "nighttime": 2, "city": 2, "eye": 2, "her": 2, "be": 2, "just": 2, "reach": 2, "to": 2, "touch": 2, "Ooh": 2, "aah": 2, "ah": 2, "wink": 1, "sleepless": 1, "hear": 1, "voice": 1, "shake": 1, "my": 1, "window": 1, "Sweet": 1, "seducing": 1, "sigh": 1, "get": 1, "into": 1, "four": 1, "wall": 1, "will": 1, "hold": 1, "tonight": 1, "town": 1, "an": 1, "apple": 1, "then": 1, "let": 1, "take": 1, "bite": 1, "stranger": 1, "electric": 1, "everywhere": 1, "see": 1, "girl": 1, "know": 1, "watch": 1, "stare": 1, "livin": 1, "morning": 1, "heart": 1, "begin": 1, "beat": 1, "shoulder": 1, "dream": 1, "of": 1, "street": 1, "Cha": 1, "cha": 1, "Da": 1, "live": 1}, "text_summarization": "[ ( t h a t   w a y ) \n ,   ( t h a t   w a y ) \n ,   w h y ? ) \n ]", "non_real_words_freq": [12, ["I'm", "livin'", "lovin'", "city's", "I'm", "Ooh-ooh,", "Cha-da-cha-sha-sha-sha-sha-sha", "(Aah-ah)", "Ooh-ooh,", "(Aah-ah)", "Da-da-da-da-da-da-da-da", "way)64Embed"]]}