{"pos_tags": {"Yeah": "ADV", ",": "PUNCT", "yeah": "INTJ", "!": "PUNCT", "\n": "SPACE", "With": "ADP", "my": "PRON", "nigga": "PROPN", "mike": "PROPN", "Hoo": "PROPN", "-": "PUNCT", "hoo": "PROPN", "Scream": "PROPN", "2Pac": "NUM", "yo": "PROPN", "Makaveli": "PROPN", "the": "DET", "dawn": "NOUN", "\n\n": "SPACE", "Tired": "ADJ", "of": "ADP", "injustice": "NOUN", "schemes": "NOUN", "The": "DET", "lies": "NOUN", "are": "AUX", "disgusting": "ADJ", "So": "ADV", "what": "PRON", "does": "AUX", "it": "PRON", "mean": "VERB", "Kicking": "VERB", "me": "PRON", "down": "ADP", "I": "PRON", "got": "VERB", "to": "PART", "get": "VERB", "up": "ADP", "As": "SCONJ", "jacked": "VERB", "as": "ADP", "sounds": "VERB", "whole": "ADJ", "system": "NOUN", "sucks": "VERB", "Woo": "PROPN", "3": "NUM", "2": "NUM", "1": "NUM", "They": "PRON", "claim": "VERB", "that": "PRON", "'m": "AUX", "violent": "ADJ", "(": "PUNCT", ")": "PUNCT", "For": "ADP", "trying": "VERB", "be": "AUX", "free": "ADJ", "come": "VERB", "And": "CCONJ", "if": "SCONJ", "you": "PRON", "stay": "VERB", "silent": "ADJ", "speak": "NOUN", "There": "PRON", "'ll": "AUX", "never": "ADV", "peace": "NOUN", "\"": "PUNCT", "fuck": "NOUN", "Why": "SCONJ", "do": "AUX", "we": "PRON", "work": "VERB", "like": "ADP", "slaves": "NOUN", "?": "PUNCT", "Fuck": "VERB", "It": "PRON", "'s": "AUX", "time": "NOUN", "hit": "VERB", "'em": "PRON", "'Cause": "SCONJ", "when": "SCONJ", "go": "VERB", "grave": "NOUN", "Nobody": "PRON", "else'll": "NOUN", "give": "VERB", "a": "DET", "You": "PRON", "might": "AUX", "also": "ADV", "like[Hook": "NOUN", ":": "PUNCT", "Michael": "PROPN", "Jackson": "PROPN", "Janet": "PROPN", "DJ": "PROPN", "Chop": "PROPN", "Up": "ADP", "]": "PUNCT", "such": "ADJ", "confusions": "NOUN", "n't": "PART", "make": "VERB", "wanna": "VERB", "scream": "VERB", "all": "DET", "niggas": "NOUN", "Your": "PRON", "bash": "NOUN", "abusin": "NOUN", "'": "PUNCT", "victimize": "NOUN", "within": "ADP", "scheme": "NOUN", ">": "PUNCT", "try": "VERB", "cope": "VERB", "with": "ADP", "every": "DET", "lie": "NOUN", "they": "PRON", "scrutinize": "VERB", "Somebody": "PRON", "please": "INTJ", "have": "VERB", "mercy": "NOUN", "just": "ADV", "ca": "AUX", "take": "VERB", "Stop": "VERB", "pressurin": "PROPN", "Just": "ADV", "stop": "VERB", "pressuring": "VERB", "fucking": "VERB", "Make": "VERB", "makes": "VERB", "Oh": "INTJ", "God": "PROPN", "believe": "VERB", "saw": "VERB", "turned": "VERB", "on": "ADP", "TV": "NOUN", "this": "DET", "evening": "NOUN", "was": "AUX", "disgusted": "VERB", "by": "ADP", "All": "DET", "[": "X", "Break": "NOUN", "x12": "NOUN", "Throw": "VERB", "your": "PRON", "hands": "NOUN", "Hook": "NOUN", "scream!)Embed": "X"}, "pos_tags_freq": {"ADV": 6, "PUNCT": 11, "INTJ": 3, "SPACE": 2, "ADP": 12, "PRON": 18, "PROPN": 15, "NUM": 4, "DET": 7, "NOUN": 27, "ADJ": 7, "AUX": 10, "VERB": 35, "PART": 2, "SCONJ": 5, "CCONJ": 1, "X": 2}, "word_frequency": {"me": 22, "stop": 15, "scream": 13, "Just": 12, "the": 9, "I": 8, "just": 7, "pressurin": 7, "with": 7, "wanna": 7, "my": 6, "it": 6, "up": 5, "all": 5, "to": 5, "fucking": 5, "nigga": 4, "that": 4, "injustice": 4, "Jackson": 4, "2Pac": 4, "niggas": 4, "Stop": 4, "we": 3, "what": 3, "as": 3, "With": 3, "do": 3, "you": 3, "You": 3, "ca": 3, "It": 3, "Scream": 3, "pressuring": 3, "Make": 3, "Tired": 2, "of": 2, "The": 2, "Yeah": 2, "violent": 2, "get": 2, "be": 2, "peace": 2, "hit": 2, "fuck": 2, "As": 2, "All": 2, "Michael": 2, "Janet": 2, "DJ": 2, "Chop": 2, "Up": 2, "such": 2, "confusions": 2, "make": 2, "Your": 2, "bash": 2, "abusin": 2, "victimize": 2, "within": 2, "scheme": 2, "try": 2, "cope": 2, "every": 2, "lie": 2, "they": 2, "scrutinize": 2, "Somebody": 2, "please": 2, "have": 2, "mercy": 2, "take": 2, "makes": 2, ",": 1, "yeah": 1, "!": 1, "\n": 1, "mike": 1, "Hoo": 1, "-": 1, "hoo": 1, "yo": 1, "Makaveli": 1, "dawn": 1, "\n\n": 1, "schemes": 1, "lies": 1, "are": 1, "disgusting": 1, "So": 1, "does": 1, "mean": 1, "Kicking": 1, "down": 1, "got": 1, "jacked": 1, "sounds": 1, "whole": 1, "system": 1, "sucks": 1, "Woo": 1, "3": 1, "2": 1, "1": 1, "They": 1, "claim": 1, "'m": 1, "(": 1, ")": 1, "For": 1, "trying": 1, "free": 1, "come": 1, "And": 1, "if": 1, "stay": 1, "silent": 1, "speak": 1, "There": 1, "'ll": 1, "never": 1, "\"": 1, "Why": 1, "work": 1, "like": 1, "slaves": 1, "?": 1, "Fuck": 1, "'s": 1, "time": 1, "'em": 1, "'Cause": 1, "when": 1, "go": 1, "grave": 1, "Nobody": 1, "else'll": 1, "give": 1, "a": 1, "might": 1, "also": 1, "like[Hook": 1, ":": 1, "]": 1, "n't": 1, "'": 1, ">": 1, "Oh": 1, "God": 1, "believe": 1, "saw": 1, "turned": 1, "on": 1, "TV": 1, "this": 1, "evening": 1, "was": 1, "disgusted": 1, "by": 1, "[": 1, "Break": 1, "x12": 1, "Throw": 1, "your": 1, "hands": 1, "Hook": 1, "scream!)Embed": 1}, "named_entities": {"mike\nHoo-hoo": "PERSON", "2Pac": "PERSON", "Makaveli": "NORP", "3": "CARDINAL", "2": "CARDINAL", "1": "CARDINAL", "Michael Jackson": "PERSON", "Janet Jackson": "PERSON", "pressurin": "PERSON", "this evening": "TIME"}, "dependency_parse": {"Yeah": {"dep": "nsubj", "head": "claim"}, ",": {"dep": "punct", "head": "stop"}, "yeah": {"dep": "intj", "head": "Yeah"}, "!": {"dep": "punct", "head": "stop"}, "\n": {"dep": "dep", "head": ")"}, "With": {"dep": "prep", "head": "Jackson"}, "my": {"dep": "poss", "head": "niggas"}, "nigga": {"dep": "appos", "head": "time"}, "mike": {"dep": "compound", "head": "hoo"}, "Hoo": {"dep": "nmod", "head": "hoo"}, "-": {"dep": "punct", "head": "hoo"}, "hoo": {"dep": "appos", "head": "nigga"}, "Scream": {"dep": "ccomp", "head": "makes"}, "2Pac": {"dep": "pobj", "head": "as"}, "yo": {"dep": "appos", "head": "nigga"}, "Makaveli": {"dep": "ROOT", "head": "Makaveli"}, "the": {"dep": "det", "head": "scheme"}, "dawn": {"dep": "appos", "head": "Makaveli"}, "\n\n": {"dep": "dep", "head": "!"}, "Tired": {"dep": "pobj", "head": "of"}, "of": {"dep": "prep", "head": "Tired"}, "injustice": {"dep": "ccomp", "head": "believe"}, "schemes": {"dep": "pobj", "head": "of"}, "The": {"dep": "det", "head": "system"}, "lies": {"dep": "nsubj", "head": "are"}, "are": {"dep": "ROOT", "head": "are"}, "disgusting": {"dep": "acomp", "head": "are"}, "So": {"dep": "advmod", "head": "mean"}, "what": {"dep": "dobj", "head": "saw"}, "does": {"dep": "aux", "head": "mean"}, "it": {"dep": "dobj", "head": "take"}, "mean": {"dep": "ROOT", "head": "mean"}, "Kicking": {"dep": "xcomp", "head": "mean"}, "me": {"dep": "nsubj", "head": "wanna"}, "down": {"dep": "prep", "head": "Kicking"}, "I": {"dep": "nsubj", "head": "take"}, "got": {"dep": "ccomp", "head": "mean"}, "to": {"dep": "aux", "head": "cope"}, "get": {"dep": "advcl", "head": "come"}, "up": {"dep": "prt", "head": "Throw"}, "As": {"dep": "mark", "head": "turned"}, "jacked": {"dep": "advcl", "head": "get"}, "as": {"dep": "prep", "head": "Jackson"}, "sounds": {"dep": "advcl", "head": "jacked"}, "whole": {"dep": "amod", "head": "system"}, "system": {"dep": "nsubj", "head": "sucks"}, "sucks": {"dep": "conj", "head": "got"}, "Woo": {"dep": "dobj", "head": "sucks"}, "3": {"dep": "pobj", "head": "Yeah"}, "2": {"dep": "preconj", "head": ","}, "1": {"dep": "nummod", "head": "They"}, "They": {"dep": "nsubj", "head": "claim"}, "claim": {"dep": "ROOT", "head": "claim"}, "that": {"dep": "nsubj", "head": "'s"}, "'m": {"dep": "ccomp", "head": "claim"}, "violent": {"dep": "conj", "head": "violent"}, "(": {"dep": "punct", "head": "wanna"}, ")": {"dep": "punct", "head": "stop"}, "For": {"dep": "prep", "head": "come"}, "trying": {"dep": "pcomp", "head": "For"}, "be": {"dep": "ROOT", "head": "be"}, "free": {"dep": "acomp", "head": "be"}, "come": {"dep": "ROOT", "head": "come"}, "And": {"dep": "ROOT", "head": "And"}, "if": {"dep": "mark", "head": "stay"}, "you": {"dep": "nsubj", "head": "wanna"}, "stay": {"dep": "advcl", "head": "And"}, "silent": {"dep": "acomp", "head": "stay"}, "speak": {"dep": "parataxis", "head": "stay"}, "There": {"dep": "expl", "head": "be"}, "'ll": {"dep": "aux", "head": "be"}, "never": {"dep": "neg", "head": "be"}, "peace": {"dep": "appos", "head": "peace"}, "\"": {"dep": "punct", "head": "be"}, "fuck": {"dep": "dobj", "head": "give"}, "Why": {"dep": "advmod", "head": "work"}, "do": {"dep": "aux", "head": "make"}, "we": {"dep": "nsubj", "head": "go"}, "work": {"dep": "ROOT", "head": "work"}, "like": {"dep": "prep", "head": "work"}, "slaves": {"dep": "pobj", "head": "like"}, "?": {"dep": "punct", "head": "make"}, "Fuck": {"dep": "ROOT", "head": "Fuck"}, "It": {"dep": "nsubj", "head": "makes"}, "'s": {"dep": "ccomp", "head": "'s"}, "time": {"dep": "attr", "head": "'s"}, "hit": {"dep": "relcl", "head": "nigga"}, "'em": {"dep": "dobj", "head": "hit"}, "'Cause": {"dep": "mark", "head": "take"}, "when": {"dep": "advmod", "head": "go"}, "go": {"dep": "advcl", "head": "give"}, "grave": {"dep": "amod", "head": "else'll"}, "Nobody": {"dep": "compound", "head": "else'll"}, "else'll": {"dep": "pobj", "head": "to"}, "give": {"dep": "advcl", "head": "'s"}, "a": {"dep": "det", "head": "fuck"}, "You": {"dep": "nsubj", "head": "try"}, "might": {"dep": "ccomp", "head": "'s"}, "also": {"dep": "advmod", "head": "might"}, "like[Hook": {"dep": "attr", "head": "'s"}, ":": {"dep": "punct", "head": "Hook"}, "Michael": {"dep": "compound", "head": "Jackson"}, "Jackson": {"dep": "conj", "head": "Jackson"}, "Janet": {"dep": "compound", "head": "Jackson"}, "DJ": {"dep": "compound", "head": "Chop"}, "Chop": {"dep": "appos", "head": "Jackson"}, "Up": {"dep": "advmod", "head": "Jackson"}, "]": {"dep": "punct", "head": "as"}, "such": {"dep": "amod", "head": "confusions"}, "confusions": {"dep": "pobj", "head": "With"}, "n't": {"dep": "neg", "head": "take"}, "make": {"dep": "ROOT", "head": "make"}, "wanna": {"dep": "ccomp", "head": "Make"}, "scream": {"dep": "xcomp", "head": "wanna"}, "all": {"dep": "predet", "head": "niggas"}, "niggas": {"dep": "nsubj", "head": "scream"}, "Your": {"dep": "poss", "head": "abusin"}, "bash": {"dep": "compound", "head": "abusin"}, "abusin": {"dep": "poss", "head": "victimize"}, "'": {"dep": "punct", "head": "pressurin"}, "victimize": {"dep": "ROOT", "head": "victimize"}, "within": {"dep": "prep", "head": "victimize"}, "scheme": {"dep": "pobj", "head": "within"}, ">": {"dep": "dep", "head": "Stop"}, "try": {"dep": "ccomp", "head": "have"}, "cope": {"dep": "xcomp", "head": "try"}, "with": {"dep": "prep", "head": "fucking"}, "every": {"dep": "det", "head": "lie"}, "lie": {"dep": "pobj", "head": "with"}, "they": {"dep": "nsubj", "head": "scrutinize"}, "scrutinize": {"dep": "relcl", "head": "lie"}, "Somebody": {"dep": "dobj", "head": "scrutinize"}, "please": {"dep": "intj", "head": "have"}, "have": {"dep": "ROOT", "head": "have"}, "mercy": {"dep": "dobj", "head": "have"}, "just": {"dep": "advmod", "head": "wanna"}, "ca": {"dep": "aux", "head": "take"}, "take": {"dep": "advcl", "head": "have"}, "Stop": {"dep": "compound", "head": "pressurin"}, "pressurin": {"dep": "poss", "head": "stop"}, "Just": {"dep": "advmod", "head": "stop"}, "stop": {"dep": "ROOT", "head": "stop"}, "pressuring": {"dep": "xcomp", "head": "stop"}, "fucking": {"dep": "xcomp", "head": "stop"}, "Make": {"dep": "ROOT", "head": "Make"}, "makes": {"dep": "ROOT", "head": "makes"}, "Oh": {"dep": "intj", "head": "believe"}, "God": {"dep": "npadvmod", "head": "Oh"}, "believe": {"dep": "ROOT", "head": "believe"}, "saw": {"dep": "csubjpass", "head": "disgusted"}, "turned": {"dep": "advcl", "head": "disgusted"}, "on": {"dep": "prt", "head": "turned"}, "TV": {"dep": "pobj", "head": "on"}, "this": {"dep": "det", "head": "evening"}, "evening": {"dep": "npadvmod", "head": "disgusted"}, "was": {"dep": "auxpass", "head": "disgusted"}, "disgusted": {"dep": "ccomp", "head": "believe"}, "by": {"dep": "agent", "head": "disgusted"}, "All": {"dep": "predet", "head": "injustice"}, "[": {"dep": "compound", "head": "Jackson"}, "Break": {"dep": "compound", "head": "x12"}, "x12": {"dep": "appos", "head": "injustice"}, "Throw": {"dep": "acl", "head": "injustice"}, "your": {"dep": "poss", "head": "hands"}, "hands": {"dep": "dobj", "head": "Throw"}, "Hook": {"dep": "pobj", "head": "["}, "scream!)Embed": {"dep": "punct", "head": "Make"}}, "text_classification": "Neutral", "text_similarity": {"2 Bad": 0.8857159738247118, "Childhood (Theme from Free Willy 2)": 0.7828710690692539, "Come Together": 0.8212072528884932, "D.S.": 0.6174699878518431, "Earth Song": 0.8464994041590304, "HIStory": 0.7277507371807759, "Little Susie": 0.7334058264579376, "Money": 0.875679589016997, "Smile": 0.8077442277443073, "Stranger in Moscow": 0.8923801363141121, "Tabloid Junkie": 0.8631350111293051, "They Don't Care About Us": 0.9005996416339255, "This Time Around (feat. The Notorious B.I.G.)": 0.8609572192540169, "You Are Not Alone": 0.8723854159694497}, "text_similarity_average": 0.8205572494638685, "word_vectors": {}, "text_lemmatization": {"I": 30, "just": 19, "stop": 19, "scream": 14, "the": 11, "with": 10, "it": 9, "fuck": 8, "up": 7, "make": 7, "wanna": 7, "all": 7, "pressurin": 7, "my": 6, "you": 6, "to": 5, "as": 5, "nigga": 4, "injustice": 4, "be": 4, "do": 4, "that": 4, "Jackson": 4, "niggas": 4, "yeah": 3, "scheme": 3, "lie": 3, "what": 3, "get": 3, "they": 3, "try": 3, "we": 3, "your": 3, "can": 3, "pressure": 3, "tired": 2, "of": 2, "violent": 2, "peace": 2, "hit": 2, "Michael": 2, "Janet": 2, "DJ": 2, "Chop": 2, "such": 2, "confusion": 2, "bash": 2, "abusin": 2, "victimize": 2, "within": 2, "cope": 2, "every": 2, "scrutinize": 2, "somebody": 2, "please": 2, "have": 2, "mercy": 2, "take": 2, "Scream": 2, "mike": 1, "Hoo": 1, "hoo": 1, "yo": 1, "Makaveli": 1, "dawn": 1, "disgusting": 1, "so": 1, "mean": 1, "kick": 1, "down": 1, "jack": 1, "sound": 1, "whole": 1, "system": 1, "suck": 1, "Woo": 1, "claim": 1, "for": 1, "free": 1, "come": 1, "and": 1, "if": 1, "stay": 1, "silent": 1, "speak": 1, "there": 1, "never": 1, "why": 1, "work": 1, "like": 1, "slave": 1, "time": 1, "when": 1, "go": 1, "grave": 1, "nobody": 1, "give": 1, "a": 1, "might": 1, "also": 1, "oh": 1, "God": 1, "believe": 1, "see": 1, "turn": 1, "on": 1, "tv": 1, "this": 1, "evening": 1, "disgust": 1, "by": 1, "break": 1, "throw": 1, "hand": 1, "hook": 1}, "text_summarization": "[ > \n s t o p   p r e s s u r i n '   m e \n j u s t   s t o p   p r e s s u r i n g   m e \n ( j u s t   s t o p   f u c k i n g   w i t h   m e ! ) \n ,   w i t h   m y   n i g g a   m i k e \n h o o - h o o ! \n s c r e a m   n i g g a ! \n 2 p a c ,   y o ! \n ,   t i r e d   o f   i n j u s t i c e \n t i r e d   o f   t h e   s c h e m e s \n t h e   l i e s   a r e   d i s g u s t i n g \n ]", "non_real_words_freq": [24, ["Hoo-hoo!", "2Pac,", "Makaveli", "I'm", "There'll", "else'll", "that's", "like[Hook:", "2Pac]", "don't", "abusin'", "pressurin'", "pressurin'", "pressurin'", "x12:", "2Pac]", "2Pac]", "don't", "abusin'", "pressurin'", "pressurin'", "pressurin'", "pressurin'", "(scream!)Embed"]]}