{"pos_tags": {"(": "PUNCT", "We": "PRON", "'ve": "AUX", "got": "VERB", "forever": "ADV", "\n": "SPACE", "Forever": "PROPN", ")": "PUNCT", "\n\n": "SPACE", "I": "PRON", "'ll": "AUX", "plant": "VERB", "you": "PRON", "a": "DET", "garden": "NOUN", "Of": "ADP", "laughter": "NOUN", "and": "CCONJ", "tears": "NOUN", "With": "ADP", "rain": "NOUN", "with": "ADP", "sunshine": "NOUN", "Love": "PROPN", "will": "AUX", "grow": "VERB", "through": "ADP", "the": "DET", "years": "NOUN", "[": "X", "Pre": "NOUN", "-": "PUNCT", "Chorus": "NOUN", "]": "PUNCT", "The": "DET", "dreams": "NOUN", "that": "SCONJ", "we": "PRON", "'re": "AUX", "dreaming": "VERB", "Have": "VERB", "time": "NOUN", "to": "PART", "come": "VERB", "true": "ADJ", "'Cause": "SCONJ", "And": "CCONJ", "is": "AUX", "meant": "VERB", "for": "ADP", "so": "ADV", "very": "ADV", "few": "ADJ", ",": "PUNCT", "mmm": "INTJ", "shall": "AUX", "have": "VERB", "music": "NOUN", "rhyme": "NOUN", "each": "DET", "other": "ADJ", "One": "NUM", "minute": "NOUN", "after": "ADP", "end": "NOUN", "of": "ADP", "ooh": "INTJ", "baby": "NOUN", "Then": "ADV", "add": "VERB", "up": "ADP", "pleasures": "NOUN", "treasure": "VERB", "sums": "NOUN", "Caring": "PROPN", "sharing": "VERB", "cake": "NOUN", "crumbs": "NOUN", "You": "PRON", "might": "AUX", "also": "ADV", "like[Pre": "NOUN", "How": "SCONJ", "lucky": "ADJ", "are": "AUX", "be": "AUX", "Me": "PRON", "it": "PRON", "million": "NUM", "tomorrows": "NOUN", "Uh": "INTJ", "yeah": "INTJ", "Yeah": "ADV", "know": "VERB", "Ah": "INTJ", "Got": "PROPN", "got)Embed": "VERB"}, "pos_tags_freq": {"PUNCT": 5, "PRON": 7, "AUX": 9, "VERB": 13, "ADV": 6, "SPACE": 2, "PROPN": 4, "DET": 4, "NOUN": 21, "ADP": 8, "CCONJ": 2, "X": 1, "SCONJ": 3, "PART": 1, "ADJ": 4, "INTJ": 5, "NUM": 2}, "word_frequency": {"got": 75, "we": 54, "We": 27, "and": 11, "forever": 10, "it": 7, "ooh": 7, "Forever": 6, "the": 5, "you": 4, "shall": 3, "have": 3, "And": 3, "is": 3, "I": 3, "that": 3, "yeah": 3, "Me": 3, "baby": 3, "Uh": 3, "a": 3, "time": 2, "The": 2, "Chorus": 2, "to": 2, "meant": 2, "for": 2, "so": 2, "very": 2, "few": 2, "know": 2, "million": 2, "tomorrows": 2, "(": 1, "'ve": 1, "\n": 1, ")": 1, "\n\n": 1, "'ll": 1, "plant": 1, "garden": 1, "Of": 1, "laughter": 1, "tears": 1, "With": 1, "rain": 1, "with": 1, "sunshine": 1, "Love": 1, "will": 1, "grow": 1, "through": 1, "years": 1, "[": 1, "Pre": 1, "-": 1, "]": 1, "dreams": 1, "'re": 1, "dreaming": 1, "Have": 1, "come": 1, "true": 1, "'Cause": 1, ",": 1, "mmm": 1, "music": 1, "rhyme": 1, "each": 1, "other": 1, "One": 1, "minute": 1, "after": 1, "end": 1, "of": 1, "Then": 1, "add": 1, "up": 1, "pleasures": 1, "treasure": 1, "sums": 1, "Caring": 1, "sharing": 1, "cake": 1, "crumbs": 1, "You": 1, "might": 1, "also": 1, "like[Pre": 1, "How": 1, "lucky": 1, "are": 1, "be": 1, "Yeah": 1, "Ah": 1, "Got": 1, "got)Embed": 1}, "named_entities": {"Love": "WORK_OF_ART", "One minute": "TIME", "million": "CARDINAL"}, "dependency_parse": {"(": {"dep": "punct", "head": "got"}, "We": {"dep": "nsubj", "head": "got"}, "'ve": {"dep": "aux", "head": "got"}, "got": {"dep": "parataxis", "head": "got"}, "forever": {"dep": "conj", "head": "Forever"}, "\n": {"dep": "dep", "head": ")"}, "Forever": {"dep": "dep", "head": "got"}, ")": {"dep": "punct", "head": "got"}, "\n\n": {"dep": "dep", "head": "baby"}, "I": {"dep": "nsubj", "head": "know"}, "'ll": {"dep": "aux", "head": "add"}, "plant": {"dep": "ROOT", "head": "plant"}, "you": {"dep": "conj", "head": "Me"}, "a": {"dep": "quantmod", "head": "million"}, "garden": {"dep": "dobj", "head": "plant"}, "Of": {"dep": "prep", "head": "garden"}, "laughter": {"dep": "pobj", "head": "Of"}, "and": {"dep": "cc", "head": "Forever"}, "tears": {"dep": "conj", "head": "laughter"}, "With": {"dep": "prep", "head": "laughter"}, "rain": {"dep": "pobj", "head": "With"}, "with": {"dep": "conj", "head": "With"}, "sunshine": {"dep": "compound", "head": "Love"}, "Love": {"dep": "nsubj", "head": "grow"}, "will": {"dep": "aux", "head": "grow"}, "grow": {"dep": "relcl", "head": "garden"}, "through": {"dep": "prep", "head": "grow"}, "the": {"dep": "det", "head": "crumbs"}, "years": {"dep": "pobj", "head": "through"}, "[": {"dep": "dep", "head": "Have"}, "Pre": {"dep": "nsubj", "head": "Have"}, "-": {"dep": "punct", "head": "Chorus"}, "Chorus": {"dep": "dep", "head": "got"}, "]": {"dep": "punct", "head": "Chorus"}, "The": {"dep": "det", "head": "cake"}, "dreams": {"dep": "nsubj", "head": "Have"}, "that": {"dep": "mark", "head": "got"}, "we": {"dep": "nsubj", "head": "got)Embed"}, "'re": {"dep": "aux", "head": "dreaming"}, "dreaming": {"dep": "relcl", "head": "dreams"}, "Have": {"dep": "ROOT", "head": "Have"}, "time": {"dep": "pobj", "head": "of"}, "to": {"dep": "aux", "head": "be"}, "come": {"dep": "relcl", "head": "time"}, "true": {"dep": "acomp", "head": "come"}, "'Cause": {"dep": "mark", "head": "got"}, "And": {"dep": "cc", "head": "got"}, "is": {"dep": "auxpass", "head": "meant"}, "meant": {"dep": "conj", "head": "got"}, "for": {"dep": "prep", "head": "meant"}, "so": {"dep": "advmod", "head": "few"}, "very": {"dep": "advmod", "head": "few"}, "few": {"dep": "pobj", "head": "for"}, ",": {"dep": "punct", "head": "got"}, "mmm": {"dep": "intj", "head": "have"}, "shall": {"dep": "aux", "head": "have"}, "have": {"dep": "relcl", "head": "rhyme"}, "music": {"dep": "dobj", "head": "have"}, "rhyme": {"dep": "dobj", "head": "have"}, "each": {"dep": "det", "head": "minute"}, "other": {"dep": "amod", "head": "minute"}, "One": {"dep": "nummod", "head": "minute"}, "minute": {"dep": "dobj", "head": "have"}, "after": {"dep": "prep", "head": "minute"}, "end": {"dep": "pobj", "head": "after"}, "of": {"dep": "prep", "head": "end"}, "ooh": {"dep": "intj", "head": "got"}, "baby": {"dep": "appos", "head": "Me"}, "Then": {"dep": "advmod", "head": "add"}, "add": {"dep": "ROOT", "head": "add"}, "up": {"dep": "prt", "head": "add"}, "pleasures": {"dep": "dobj", "head": "add"}, "treasure": {"dep": "conj", "head": "add"}, "sums": {"dep": "compound", "head": "Caring"}, "Caring": {"dep": "nsubj", "head": "sharing"}, "sharing": {"dep": "ccomp", "head": "treasure"}, "cake": {"dep": "dobj", "head": "sharing"}, "crumbs": {"dep": "conj", "head": "cake"}, "You": {"dep": "nsubj", "head": "might"}, "might": {"dep": "aux", "head": "Chorus"}, "also": {"dep": "advmod", "head": "might"}, "like[Pre": {"dep": "compound", "head": "Chorus"}, "How": {"dep": "advmod", "head": "lucky"}, "lucky": {"dep": "acomp", "head": "are"}, "are": {"dep": "relcl", "head": "Chorus"}, "be": {"dep": "xcomp", "head": "are"}, "Me": {"dep": "ROOT", "head": "Me"}, "it": {"dep": "dobj", "head": "got"}, "million": {"dep": "nummod", "head": "tomorrows"}, "tomorrows": {"dep": "dobj", "head": "got"}, "Uh": {"dep": "intj", "head": "got"}, "yeah": {"dep": "intj", "head": "got"}, "Yeah": {"dep": "advmod", "head": "got"}, "know": {"dep": "ccomp", "head": "got"}, "Ah": {"dep": "intj", "head": "got"}, "Got": {"dep": "nsubj", "head": "got"}, "got)Embed": {"dep": "ROOT", "head": "got)Embed"}}, "text_classification": "Neutral", "text_similarity": {"Cinderella Stay Awhile": 0.7440270738795954, "Dapper Dan": 0.7306080247971601, "Dear Michael": 0.7124593689209011, "I'll Come Home to You": 0.7561523611925041, "Just a Little Bit of You": 0.7042560992307941, "One Day in Your Life": 0.7065884271078324, "Take Me Back": 0.6941524673757355, "We're Almost There": 0.8464243916621532, "You Are There": 0.7472794678583751}, "text_similarity_average": 0.7379941868916724, "word_vectors": {}, "text_lemmatization": {"we": 81, "get": 75, "and": 14, "forever": 10, "the": 7, "ooh": 7, "it": 7, "Forever": 6, "I": 6, "you": 5, "be": 5, "have": 4, "yeah": 4, "a": 3, "that": 3, "shall": 3, "baby": 3, "uh": 3, "of": 2, "with": 2, "chorus": 2, "dream": 2, "time": 2, "to": 2, "mean": 2, "for": 2, "so": 2, "very": 2, "few": 2, "million": 2, "tomorrow": 2, "know": 2, "plant": 1, "garden": 1, "laughter": 1, "tear": 1, "rain": 1, "sunshine": 1, "Love": 1, "will": 1, "grow": 1, "through": 1, "year": 1, "Pre": 1, "come": 1, "true": 1, "mmm": 1, "music": 1, "rhyme": 1, "each": 1, "other": 1, "one": 1, "minute": 1, "after": 1, "end": 1, "then": 1, "add": 1, "up": 1, "pleasure": 1, "treasure": 1, "sum": 1, "Caring": 1, "share": 1, "cake": 1, "crumb": 1, "might": 1, "also": 1, "how": 1, "lucky": 1, "ah": 1, "Got": 1}, "text_summarization": "[ w e ' v e   g o t ,   w e ' v e   g o t ,   w e ' v e   g o t \n ( w e   g o t ,   w e   g o t ,   w e   g o t ,   o o h )   g o t ,   g o t ,   y e a h \n ( w e   g o t ,   w e   g o t ,   w e   g o t ) ,   u h \n ( w e   g o t ,   w e   g o t ,   w e   g o t ,   o o h ) \n ( w e   g o t ,   w e   g o t ,   w e   g o t ) ,   w e   g o t   a   m i l l i o n   t o m o r r o w s \n ( w e   g o t ,   w e   g o t ,   w e   g o t ,   w e   g o t   i t ) ]", "non_real_words_freq": [11, ["(We've", "[Pre-Chorus]", "we've", "mmm", "ooh-ooh,", "like[Pre-Chorus]", "we've", "We've", "we've", "we've", "got)Embed"]]}