{"pos_tags": {"Oh": "INTJ", "man": "NOUN", "!": "PUNCT", "Look": "VERB", "at": "ADP", "that": "SCONJ", "girl": "NOUN", "right": "ADJ", "there": "ADV", "\n": "SPACE", "Goodness": "PROPN", "gracious": "ADJ", "Uh": "INTJ", "That": "PRON", "'s": "AUX", "fine": "ADJ", ",": "PUNCT", "it": "PRON", "she": "PRON", "just": "ADV", "too": "ADV", "She": "PRON", "know": "VERB", "is": "AUX", "banging": "VERB", "off": "ADP", "the": "DET", "hook": "NOUN", "looks": "VERB", "good": "ADJ", "you": "PRON", "'re": "AUX", "Ahh": "ADV", "-": "PUNCT", "uh": "INTJ", "I": "PRON", "bet": "VERB", "ca": "AUX", "n't": "PART", "nobody": "PRON", "get": "VERB", "Chris": "PROPN", "can": "AUX", "her": "PRON", "You": "PRON", "Mike": "PROPN", "guarantee": "VERB", "Watch": "NOUN", "me": "PRON", "never": "ADV", "Neverland": "PROPN", "All": "DET", "Shamone": "PROPN", "then": "ADV", "shamone": "PROPN", "\n\n": "SPACE", "[": "X", "Intro": "PROPN", ":": "PUNCT", "Michael": "PROPN", "Jackson": "PROPN", "]": "PUNCT", "do": "VERB", "think": "VERB", "they": "PRON", "ready": "ADJ", "for": "ADP", "this": "PRON", "one": "NUM", "Darkchild": "NOUN", "like": "ADP", "oh": "INTJ", "My": "PRON", "life": "NOUN", "will": "AUX", "be": "AUX", "same": "ADJ", "'Cause": "SCONJ", "came": "VERB", "and": "CCONJ", "changed": "VERB", "The": "DET", "way": "NOUN", "walk": "VERB", "talk": "VERB", "And": "CCONJ", "not": "PART", "explain": "VERB", "things": "NOUN", "feel": "VERB", "But": "CCONJ", "true": "ADJ", "So": "ADV", "stay": "VERB", "with": "ADP", "fulfill": "VERB", "my": "PRON", "dreams": "NOUN", "'ll": "AUX", "all": "PRON", "need": "VERB", "might": "AUX", "also": "ADV", "like[Pre": "NOUN", "Chorus": "NOUN", "ooh": "INTJ", "feels": "VERB", "so": "ADV", "(": "PUNCT", "Girl": "NOUN", ")": "PUNCT", "'ve": "AUX", "searched": "VERB", "perfect": "ADJ", "love": "NOUN", "Like": "ADP", "Have": "AUX", "finally": "ADV", "found": "VERB", "a": "DET", "time": "NOUN", "See": "NOUN", "come": "VERB", "on": "ADP", "rocked": "VERB", "world": "NOUN", "did": "VERB", "everything": "PRON", "own": "VERB", "give": "VERB", "rarest": "ADJ", "who": "PRON", "'d": "AUX", "find": "VERB", "Someone": "PRON", "to": "PART", "call": "VERB", "mine": "NOUN", "Come": "VERB", "In": "ADP", "knew": "VERB", "would": "AUX", "bring": "VERB", "Such": "DET", "happiness": "NOUN", "tried": "VERB", "keep": "VERB", "sanity": "NOUN", "waited": "VERB", "patiently": "ADV", "seems": "VERB", "complete": "ADJ", "A": "DET", "because": "SCONJ", "of": "ADP", "Keep": "VERB", "doing": "VERB", "what": "PRON", "Pre": "NOUN", "Searched": "VERB", "awesomely": "ADV", "Bridge": "PROPN", "magic": "NOUN", "in": "ADP", "air": "NOUN", "enough": "ADJ", "why": "SCONJ", "always": "ADV", "have": "VERB", "here": "ADV", "hoo": "PROPN", "baby": "NOUN", "yeah": "INTJ", "Know": "VERB", "Hoo": "PROPN", "rock": "VERB", "lovin'": "VERB", "Give": "VERB", "Yeah": "INTJ", "Baby": "PROPN", "mine45Embed": "VERB"}, "pos_tags_freq": {"INTJ": 7, "NOUN": 23, "PUNCT": 7, "VERB": 44, "ADP": 10, "SCONJ": 4, "ADJ": 11, "ADV": 14, "SPACE": 2, "PROPN": 13, "PRON": 19, "AUX": 13, "DET": 6, "PART": 3, "X": 1, "NUM": 1, "CCONJ": 3}, "word_frequency": {"I": 64, "you": 62, "my": 35, "You": 30, "world": 29, "rocked": 27, "know": 19, "love": 19, "to": 19, "girl": 18, "did": 17, "And": 17, "The": 17, "oh": 16, "think": 15, "who": 14, "like": 14, "give": 13, "find": 13, "everything": 12, "own": 12, "rarest": 12, "Someone": 12, "call": 12, "that": 11, "mine": 11, "Oh": 10, "me": 8, "on": 8, "the": 7, "get": 7, "Michael": 7, "Jackson": 7, "it": 7, "life": 6, "for": 5, "right": 5, "Girl": 5, "all": 5, "Chorus": 5, "way": 5, "She": 4, "uh": 4, "ca": 4, "perfect": 4, "come": 4, "yeah": 4, "ooh": 4, "Come": 4, "baby": 4, "fine": 3, "can": 3, "finally": 3, "found": 3, "so": 3, "this": 3, "is": 3, "never": 3, "Look": 3, "hoo": 3, "man": 2, "at": 2, "she": 2, "too": 2, "bet": 2, "her": 2, "Watch": 2, "be": 2, "All": 2, "feels": 2, "time": 2, "My": 2, "true": 2, "do": 2, "Have": 2, "searched": 2, "Such": 2, "a": 2, "So": 2, "feel": 2, "That": 2, "have": 2, "what": 2, "Hoo": 2, "rock": 2, "talk": 2, "!": 1, "there": 1, "\n": 1, "Goodness": 1, "gracious": 1, "Uh": 1, "'s": 1, ",": 1, "just": 1, "banging": 1, "off": 1, "hook": 1, "looks": 1, "good": 1, "'re": 1, "Ahh": 1, "-": 1, "n't": 1, "nobody": 1, "Chris": 1, "Mike": 1, "guarantee": 1, "Neverland": 1, "Shamone": 1, "then": 1, "shamone": 1, "\n\n": 1, "[": 1, "Intro": 1, ":": 1, "]": 1, "they": 1, "ready": 1, "one": 1, "Darkchild": 1, "will": 1, "same": 1, "'Cause": 1, "came": 1, "and": 1, "changed": 1, "walk": 1, "not": 1, "explain": 1, "things": 1, "But": 1, "stay": 1, "with": 1, "fulfill": 1, "dreams": 1, "'ll": 1, "need": 1, "might": 1, "also": 1, "like[Pre": 1, "(": 1, ")": 1, "'ve": 1, "Like": 1, "See": 1, "'d": 1, "In": 1, "knew": 1, "would": 1, "bring": 1, "happiness": 1, "tried": 1, "keep": 1, "sanity": 1, "waited": 1, "patiently": 1, "seems": 1, "complete": 1, "A": 1, "because": 1, "of": 1, "Keep": 1, "doing": 1, "Pre": 1, "Searched": 1, "awesomely": 1, "Bridge": 1, "magic": 1, "in": 1, "air": 1, "enough": 1, "why": 1, "always": 1, "here": 1, "Know": 1, "lovin'": 1, "Give": 1, "Yeah": 1, "Baby": 1, "mine45Embed": 1}, "named_entities": {"Chris": "PERSON", "Mike\nI": "PERSON", "Shamone": "PERSON", "Michael Jackson": "PERSON", "one": "CARDINAL"}, "dependency_parse": {"Oh": {"dep": "intj", "head": "love"}, "man": {"dep": "ROOT", "head": "man"}, "!": {"dep": "punct", "head": "shamone"}, "Look": {"dep": "xcomp", "head": "give"}, "at": {"dep": "prep", "head": "Look"}, "that": {"dep": "mark", "head": "is"}, "girl": {"dep": "npadvmod", "head": "Come"}, "right": {"dep": "acomp", "head": "'s"}, "there": {"dep": "advmod", "head": "Look"}, "\n": {"dep": "dep", "head": "find"}, "Goodness": {"dep": "ROOT", "head": "Goodness"}, "gracious": {"dep": "amod", "head": "Goodness"}, "Uh": {"dep": "ROOT", "head": "Uh"}, "That": {"dep": "nsubj", "head": "'s"}, "'s": {"dep": "ccomp", "head": "know"}, "fine": {"dep": "ccomp", "head": "know"}, ",": {"dep": "punct", "head": "love"}, "it": {"dep": "dobj", "head": "Give"}, "she": {"dep": "nsubj", "head": "fine"}, "just": {"dep": "advmod", "head": "fine"}, "too": {"dep": "advmod", "head": "know"}, "She": {"dep": "nsubj", "head": "looks"}, "know": {"dep": "parataxis", "head": "did"}, "is": {"dep": "ccomp", "head": "know"}, "banging": {"dep": "ROOT", "head": "banging"}, "off": {"dep": "prep", "head": "'s"}, "the": {"dep": "det", "head": "girl"}, "hook": {"dep": "pobj", "head": "off"}, "looks": {"dep": "ccomp", "head": "'re"}, "good": {"dep": "acomp", "head": "looks"}, "you": {"dep": "pobj", "head": "like"}, "'re": {"dep": "ccomp", "head": "think"}, "Ahh": {"dep": "nmod", "head": "bet"}, "-": {"dep": "punct", "head": "oh"}, "uh": {"dep": "intj", "head": "bet"}, "I": {"dep": "nsubj", "head": "find"}, "bet": {"dep": "ROOT", "head": "bet"}, "ca": {"dep": "aux", "head": "get"}, "n't": {"dep": "neg", "head": "think"}, "nobody": {"dep": "nsubj", "head": "get"}, "get": {"dep": "ROOT", "head": "get"}, "Chris": {"dep": "dobj", "head": "get"}, "can": {"dep": "aux", "head": "explain"}, "her": {"dep": "nsubj", "head": "right"}, "You": {"dep": "nsubj", "head": "rocked"}, "Mike": {"dep": "compound", "head": "I"}, "guarantee": {"dep": "ROOT", "head": "guarantee"}, "Watch": {"dep": "npadvmod", "head": "think"}, "me": {"dep": "pobj", "head": "to"}, "never": {"dep": "neg", "head": "get"}, "Neverland": {"dep": "npadvmod", "head": "get"}, "All": {"dep": "predet", "head": "life"}, "Shamone": {"dep": "ROOT", "head": "Shamone"}, "then": {"dep": "advmod", "head": "Shamone"}, "shamone": {"dep": "conj", "head": "Shamone"}, "\n\n": {"dep": "dep", "head": ")"}, "[": {"dep": "punct", "head": "Chorus"}, "Intro": {"dep": "dobj", "head": "Watch"}, ":": {"dep": "punct", "head": "Chorus"}, "Michael": {"dep": "compound", "head": "Jackson"}, "Jackson": {"dep": "appos", "head": "Chorus"}, "]": {"dep": "dep", "head": "rocked"}, "do": {"dep": "ccomp", "head": "doing"}, "think": {"dep": "relcl", "head": "love"}, "they": {"dep": "nsubj", "head": "'re"}, "ready": {"dep": "acomp", "head": "'re"}, "for": {"dep": "prep", "head": "Searched"}, "this": {"dep": "nsubj", "head": "is"}, "one": {"dep": "nummod", "head": "Darkchild"}, "Darkchild": {"dep": "pobj", "head": "for"}, "like": {"dep": "prep", "head": "Someone"}, "oh": {"dep": "intj", "head": "oh"}, "My": {"dep": "poss", "head": "life"}, "life": {"dep": "pobj", "head": "for"}, "will": {"dep": "aux", "head": "be"}, "be": {"dep": "ccomp", "head": "fulfill"}, "same": {"dep": "amod", "head": "'Cause"}, "'Cause": {"dep": "mark", "head": "rocked"}, "came": {"dep": "ROOT", "head": "came"}, "and": {"dep": "cc", "head": "came"}, "changed": {"dep": "conj", "head": "came"}, "The": {"dep": "det", "head": "love"}, "way": {"dep": "npadvmod", "head": "lovin'"}, "walk": {"dep": "relcl", "head": "way"}, "talk": {"dep": "relcl", "head": "way"}, "And": {"dep": "cc", "head": "give"}, "not": {"dep": "neg", "head": "explain"}, "explain": {"dep": "ccomp", "head": "'s"}, "things": {"dep": "dobj", "head": "explain"}, "feel": {"dep": "ccomp", "head": "know"}, "But": {"dep": "cc", "head": "you"}, "true": {"dep": "acomp", "head": "'s"}, "So": {"dep": "advmod", "head": "girl"}, "stay": {"dep": "ccomp", "head": "'s"}, "with": {"dep": "prep", "head": "stay"}, "fulfill": {"dep": "conj", "head": "stay"}, "my": {"dep": "poss", "head": "world"}, "dreams": {"dep": "dobj", "head": "fulfill"}, "'ll": {"dep": "aux", "head": "get"}, "all": {"dep": "advmod", "head": "in"}, "need": {"dep": "relcl", "head": "all"}, "might": {"dep": "ccomp", "head": "be"}, "also": {"dep": "advmod", "head": "might"}, "like[Pre": {"dep": "compound", "head": "Chorus"}, "Chorus": {"dep": "appos", "head": "That"}, "ooh": {"dep": "intj", "head": "yeah"}, "feels": {"dep": "ROOT", "head": "feels"}, "so": {"dep": "advmod", "head": "right"}, "(": {"dep": "punct", "head": "baby"}, "Girl": {"dep": "oprd", "head": "call"}, ")": {"dep": "punct", "head": "baby"}, "'ve": {"dep": "aux", "head": "waited"}, "searched": {"dep": "relcl", "head": "love"}, "perfect": {"dep": "amod", "head": "love"}, "love": {"dep": "dobj", "head": "give"}, "Like": {"dep": "prep", "head": "I"}, "Have": {"dep": "aux", "head": "found"}, "finally": {"dep": "advmod", "head": "found"}, "found": {"dep": "ccomp", "head": "think"}, "a": {"dep": "det", "head": "love"}, "time": {"dep": "pobj", "head": "In"}, "See": {"dep": "conj", "head": "found"}, "come": {"dep": "dep", "head": "Come"}, "on": {"dep": "prt", "head": "Come"}, "rocked": {"dep": "ccomp", "head": "call"}, "world": {"dep": "dobj", "head": "rocked"}, "did": {"dep": "ROOT", "head": "did"}, "everything": {"dep": "dep", "head": "give"}, "own": {"dep": "relcl", "head": "everything"}, "give": {"dep": "ROOT", "head": "give"}, "rarest": {"dep": "amod", "head": "love"}, "who": {"dep": "nsubj", "head": "think"}, "'d": {"dep": "aux", "head": "find"}, "find": {"dep": "ccomp", "head": "think"}, "Someone": {"dep": "dobj", "head": "find"}, "to": {"dep": "aux", "head": "call"}, "call": {"dep": "xcomp", "head": "find"}, "mine": {"dep": "dobj", "head": "call"}, "Come": {"dep": "dep", "head": "rocked"}, "In": {"dep": "prep", "head": "knew"}, "knew": {"dep": "ccomp", "head": "seems"}, "would": {"dep": "aux", "head": "bring"}, "bring": {"dep": "ccomp", "head": "knew"}, "Such": {"dep": "predet", "head": "love"}, "happiness": {"dep": "dobj", "head": "bring"}, "tried": {"dep": "ccomp", "head": "knew"}, "keep": {"dep": "xcomp", "head": "tried"}, "sanity": {"dep": "dobj", "head": "keep"}, "waited": {"dep": "ccomp", "head": "keep"}, "patiently": {"dep": "advmod", "head": "waited"}, "seems": {"dep": "ROOT", "head": "seems"}, "complete": {"dep": "acomp", "head": "is"}, "A": {"dep": "det", "head": "love"}, "because": {"dep": "prep", "head": "'s"}, "of": {"dep": "pcomp", "head": "because"}, "Keep": {"dep": "pcomp", "head": "because"}, "doing": {"dep": "xcomp", "head": "Keep"}, "what": {"dep": "dobj", "head": "did"}, "Pre": {"dep": "compound", "head": "Chorus"}, "Searched": {"dep": "parataxis", "head": "found"}, "awesomely": {"dep": "acomp", "head": "'s"}, "Bridge": {"dep": "npadvmod", "head": "know"}, "magic": {"dep": "dobj", "head": "feel"}, "in": {"dep": "prep", "head": "magic"}, "air": {"dep": "nmod", "head": "girl"}, "enough": {"dep": "acomp", "head": "get"}, "why": {"dep": "advmod", "head": "have"}, "always": {"dep": "advmod", "head": "have"}, "have": {"dep": "xcomp", "head": "have"}, "here": {"dep": "advmod", "head": "have"}, "hoo": {"dep": "dobj", "head": "find"}, "baby": {"dep": "dobj", "head": "did"}, "yeah": {"dep": "ROOT", "head": "yeah"}, "Know": {"dep": "ROOT", "head": "Know"}, "Hoo": {"dep": "nmod", "head": "hoo"}, "rock": {"dep": "parataxis", "head": "rock"}, "lovin'": {"dep": "relcl", "head": "way"}, "Give": {"dep": "xcomp", "head": "did"}, "Yeah": {"dep": "ROOT", "head": "Yeah"}, "Baby": {"dep": "nmod", "head": "baby"}, "mine45Embed": {"dep": "xcomp", "head": "call"}}, "text_classification": "Positive", "text_similarity": {"2000 Watts": 0.6079818182794451, "Break of Dawn": 0.9127827358180007, "Butterflies": 0.9212140496071324, "Cry": 0.8777429993563785, "Don't Walk Away": 0.9152756748495945, "Heartbreaker": 0.895117858276357, "Heaven Can Wait": 0.9399780211774756, "Invincible": 0.9416188888561988, "Privacy": 0.9379030661623418, "Speechless": 0.9130391777027528, "The Lost Children": 0.7373091260546594, "Threatened": 0.8807579583775808, "Unbreakable": 0.9264693322782245, "Whatever Happens": 0.876017228722352, "You Are My Life": 0.8529585568525454}, "text_similarity_average": 0.8757444328247359, "word_vectors": {}, "text_lemmatization": {"you": 92, "I": 72, "my": 37, "rock": 29, "world": 29, "oh": 26, "the": 24, "girl": 23, "know": 21, "do": 20, "love": 19, "to": 19, "and": 18, "find": 16, "think": 15, "like": 15, "give": 14, "who": 14, "that": 13, "everything": 12, "own": 12, "rarest": 12, "someone": 12, "call": 12, "mine": 11, "come": 9, "on": 8, "it": 7, "can": 7, "get": 7, "all": 7, "Michael": 7, "Jackson": 7, "she": 6, "life": 6, "right": 5, "uh": 5, "be": 5, "for": 5, "way": 5, "so": 5, "chorus": 5, "yeah": 5, "look": 4, "feel": 4, "ooh": 4, "perfect": 4, "have": 4, "baby": 4, "fine": 3, "never": 3, "this": 3, "search": 3, "finally": 3, "a": 3, "hoo": 3, "man": 2, "at": 2, "too": 2, "bet": 2, "her": 2, "watch": 2, "talk": 2, "true": 2, "time": 2, "in": 2, "such": 2, "keep": 2, "what": 2, "Hoo": 2, "there": 1, "Goodness": 1, "gracious": 1, "just": 1, "bang": 1, "off": 1, "hook": 1, "good": 1, "ahh": 1, "nobody": 1, "Chris": 1, "Mike": 1, "guarantee": 1, "Neverland": 1, "Shamone": 1, "then": 1, "shamone": 1, "Intro": 1, "they": 1, "ready": 1, "one": 1, "darkchild": 1, "will": 1, "same": 1, "change": 1, "walk": 1, "not": 1, "explain": 1, "thing": 1, "but": 1, "stay": 1, "with": 1, "fulfill": 1, "dream": 1, "need": 1, "might": 1, "also": 1, "see": 1, "would": 1, "bring": 1, "happiness": 1, "try": 1, "sanity": 1, "wait": 1, "patiently": 1, "seem": 1, "complete": 1, "because": 1, "of": 1, "Pre": 1, "awesomely": 1, "Bridge": 1, "magic": 1, "air": 1, "enough": 1, "why": 1, "always": 1, "here": 1, "Baby": 1}, "text_summarization": "[ y e a h ,   o o h ) \n ,   w a t c h   m e   g e t   t h a t   g i r l \n ,   k n o w   y o u   d i d   b a b y ) \n ]", "non_real_words_freq": [39, ["you're", "Ahh-uh-uh-uh-uh,", "never-Neverland,", "Shamone,", "shamone!", "don't", "they're", "Darkchild,", "oh-oh,", "oh-oh", "Oh-oh-oh", "you'll", "like[Pre-Chorus:", "Oh-oh-oh-oh-ooh,", "I've", "Oh-oh-oh-oh-ooh,", "who'd", "who'd", "I've", "that's", "[Pre-Chorus:", "who'd", "Oh-oh-oh,", "who'd", "(Oh-oh-oh)", "that's", "who'd", "who'd", "who'd", "who'd", "That's", "who'd", "who'd", "who'd", "who'd", "lovin'", "who'd", "who'd", "mine45Embed"]]}